MANIFEST.in
README.rst
bootstrap-buildout.py
buildout.cfg
setup.py
version.txt
antispoofing/__init__.py
antispoofing.fusion_faceverif.egg-info/PKG-INFO
antispoofing.fusion_faceverif.egg-info/SOURCES.txt
antispoofing.fusion_faceverif.egg-info/dependency_links.txt
antispoofing.fusion_faceverif.egg-info/entry_points.txt
antispoofing.fusion_faceverif.egg-info/requires.txt
antispoofing.fusion_faceverif.egg-info/top_level.txt
antispoofing/fusion_faceverif/__init__.py
antispoofing/fusion_faceverif/helpers/__init__.py
antispoofing/fusion_faceverif/helpers/fusion_utils.py
antispoofing/fusion_faceverif/script/__init__.py
antispoofing/fusion_faceverif/script/and_decision_epsc.py
antispoofing/fusion_faceverif/script/and_decision_epsc_cs.py
antispoofing/fusion_faceverif/script/and_decision_fusion.py
antispoofing/fusion_faceverif/script/antispoof_threshold.py
antispoofing/fusion_faceverif/script/dir_to_four_column.py
antispoofing/fusion_faceverif/script/faceverif_threshold.py
antispoofing/fusion_faceverif/script/four_column_to_dir_structure.py
antispoofing/fusion_faceverif/script/fusion_fvas.py
antispoofing/fusion_faceverif/script/plot_on_demand.py
antispoofing/fusion_faceverif/script/scatter_plot.py