Metadata-Version: 1.0
Name: antispoofing.fusion-faceverif
Version: 3.0.2
Summary: Decision and score-level fusion tools for joint operation of face verification and anti-spoofing system
Home-page: http://github.com/bioidiap/antispoofing.fusion_faceverif
Author: Ivana Chingovska
Author-email: Ivana Chingovska <ivana.chingovska@idiap.ch>
License: LICENSE.txt
Platform: UNKNOWN
